cnda_dl-1.2.0.dist-info/METADATA
cnda_dl-1.2.0.dist-info/WHEEL
cnda_dl-1.2.0.dist-info/entry_points.txt
cnda_dl-1.2.0.dist-info/licenses/LICENSE
cnda_dl/.ruff_cache/.gitignore
cnda_dl/.ruff_cache/0.9.9/15962950311086395899
cnda_dl/.ruff_cache/CACHEDIR.TAG
cnda_dl/__init__.py
cnda_dl/cli.py
cnda_dl/formatters.py
cnda_dl/zip_utils.py
cnda_dl-1.2.0.dist-info/RECORD
